linkedScraper/__init__.py
linkedScraper/chromedriver
linkedScraper/scraper.py
linkedScraper-0.0.2.dist-info/METADATA
linkedScraper-0.0.2.dist-info/WHEEL
linkedScraper-0.0.2.dist-info/top_level.txt
linkedScraper-0.0.2.dist-info/RECORD
