Metadata-Version: 2.1
Name: linkedScraper
Version: 0.0.2
Summary: A package to scrape LinkedIn!
Home-page: https://github.com/noahxl10/linkedin-scraper
Author: Noah Alex
Author-email: noahxl10@gmail.com
License: UNKNOWN
Platform: UNKNOWN
Classifier: Programming Language :: Python :: 3
Classifier: License :: OSI Approved :: MIT License
Classifier: Operating System :: OS Independent
Requires-Python: >=3.1
Requires-Dist: pandas
Requires-Dist: parsel
Requires-Dist: selenium
